cirrus/__init__.py
cirrus/__version__.py
cirrus/exceptions.py
cirrus/py.typed
cirrus/lambda_functions/__init__.py
cirrus/lambda_functions/api.py
cirrus/lambda_functions/post_batch.py
cirrus/lambda_functions/pre_batch.py
cirrus/lambda_functions/process.py
cirrus/lambda_functions/update_state.py
cirrus/lib/__init__.py
cirrus/lib/cirrus_payload.py
cirrus/lib/enums.py
cirrus/lib/errors.py
cirrus/lib/eventdb.py
cirrus/lib/events.py
cirrus/lib/logging.py
cirrus/lib/payload_manager.py
cirrus/lib/statedb.py
cirrus/lib/utils.py
cirrus/management/__init__.py
cirrus/management/__main__.py
cirrus/management/cli.py
cirrus/management/deployment.py
cirrus/management/deployment_pointer.py
cirrus/management/exceptions.py
cirrus/management/py.typed
cirrus/management/task_logs.py
cirrus/management/commands/__init__.py
cirrus/management/commands/deployments.py
cirrus/management/commands/manage.py
cirrus/management/commands/payload.py
cirrus/management/utils/__init__.py
cirrus/management/utils/click.py
cirrus/management/utils/logging.py
cirrus/management/utils/logging_classes.py
cirrus/management/utils/manage.py
cirrus/management/utils/templating.py
cirrus_geo-1.3.1.dist-info/METADATA
cirrus_geo-1.3.1.dist-info/WHEEL
cirrus_geo-1.3.1.dist-info/entry_points.txt
cirrus_geo-1.3.1.dist-info/licenses/LICENSE
cirrus_geo-1.3.1.dist-info/RECORD
