Metadata-Version: 2.4
Name: cirrus-geo
Version: 1.3.1
Summary: AWS-native STAC-based processing pipeline
Project-URL: Repository, https://github.com/cirrus-geo/cirrus-geo
Author: Matthew Hanson (matthewhanson)
Author-email: Jarrett Keifer <jkeifer@element84.com>
License: Apache License 2.0
License-File: LICENSE
Keywords: cirrus,geospatial,stac,workflow
Classifier: Intended Audience :: Developers
Classifier: License :: OSI Approved :: Apache Software License
Classifier: Programming Language :: Python :: 3
Requires-Python: >=3.12
Requires-Dist: boto3
Requires-Dist: boto3-utils
Requires-Dist: jsonpath-ng
Requires-Dist: python-json-logger
Requires-Dist: stactask>=0.7.0
Provides-Extra: cli
Requires-Dist: backoff; extra == 'cli'
Requires-Dist: click-option-group; extra == 'cli'
Requires-Dist: click>=8.2.0; extra == 'cli'
